austere/__init__.py
austere/austere-gui.py
austere/austere-plugin.py
austere/austere.py
austere/create_depthmap.py
austere/depthmap/README
austere/depthmap/blackhole.png
austere/depthmap/bumps.png
austere/depthmap/cube.png
austere/depthmap/donut.png
austere/depthmap/ic.png
austere/depthmap/rings.png
austere/depthmap/ripples.png
austere/depthmap/shark.png
austere/depthmap/sombrero.png
austere/depthmap/upanddown.png
austere/depthmap/vortex.png
austere/wallpaper/README
austere/wallpaper/birds.png
austere/wallpaper/citrus.png
austere/wallpaper/clouds.png
austere/wallpaper/coffee.png
austere/wallpaper/flowers.png
austere/wallpaper/fruit.png
austere/wallpaper/hieroglyphs.png
austere/wallpaper/houses.png
austere/wallpaper/ink_splashes.png
austere/wallpaper/quilt.png
austere/wallpaper/quilt_drops.png
austere/wallpaper/school.png
austere/wallpaper/underwater_world.png
austere/wallpaper/water.png
austere3d-1.0.1.dist-info/LICENSE
austere3d-1.0.1.dist-info/METADATA
austere3d-1.0.1.dist-info/WHEEL
austere3d-1.0.1.dist-info/top_level.txt
austere3d-1.0.1.dist-info/RECORD
