Metadata-Version: 2.1
Name: austere3d
Version: 1.0.1
Summary: Create your own AUtoSTEREograms
Home-page: https://gitlab.com/RolfSander/austere
Author: Rolf Sander
Author-email: mail@rolf-sander.net
License: UNKNOWN
Platform: UNKNOWN
Classifier: Programming Language :: Python :: 3.6
Classifier: License :: OSI Approved :: GNU General Public License (GPL)
Classifier: Operating System :: OS Independent
Classifier: Natural Language :: English
Classifier: Topic :: Multimedia :: Graphics
Requires-Python: >=3.6
Requires-Dist: matplotlib
Requires-Dist: numpy
Requires-Dist: pillow
Requires-Dist: scipy
